{
  "updated_at": "2026-02-09T19:18:34",
  "source": "espn",
  "teams": {
    "ATL": [
      {
        "player": "Dyson Daniels",
        "status": "OUT",
        "reason": "Right ankle (inflammation)",
        "date": "2026-02-09T23:32Z"
      },
      {
        "player": "Jalen Johnson",
        "status": "OUT",
        "reason": "Left knee (inflammation)",
        "date": "2026-02-09T23:29Z"
      },
      {
        "player": "Jonathan Kuminga",
        "status": "OUT",
        "reason": "Left knee (bruise)",
        "date": "2026-02-07T21:14Z"
      }
    ],
    "BOS": [
      {
        "player": "Jayson Tatum",
        "status": "OUT",
        "reason": "Right achilles (surgery)",
        "date": "2026-02-09T22:15Z"
      },
      {
        "player": "Sam Hauser",
        "status": "QUESTIONABLE",
        "reason": "back (spasms)",
        "date": "2026-02-09T14:18Z"
      },
      {
        "player": "John Tonje",
        "status": "QUESTIONABLE",
        "reason": "undisclosed",
        "date": "2026-02-08T18:52Z"
      }
    ],
    "BKN": [
      {
        "player": "Michael Porter Jr.",
        "status": "OUT",
        "reason": "Right knee (tendinitis)",
        "date": "2026-02-08T22:19Z"
      },
      {
        "player": "Egor Demin",
        "status": "OUT",
        "reason": "rest",
        "date": "2026-02-08T22:14Z"
      }
    ],
    "CHA": [
      {
        "player": "Liam McNeeley",
        "status": "OUT",
        "reason": "Left ankle (sprain)",
        "date": "2026-02-09T16:40Z"
      },
      {
        "player": "Coby White",
        "status": "OUT",
        "reason": "Left calf (strain)",
        "date": "2026-02-05T20:58Z"
      }
    ],
    "CHI": [
      {
        "player": "Josh Giddey",
        "status": "OUT",
        "reason": "Left hamstring (strain)",
        "date": "2026-02-09T23:07Z"
      },
      {
        "player": "Tre Jones",
        "status": "OUT",
        "reason": "Left hamstring (strain)",
        "date": "2026-02-09T23:06Z"
      },
      {
        "player": "Jalen Smith",
        "status": "OUT",
        "reason": "Right calf (strain)",
        "date": "2026-02-09T23:05Z"
      },
      {
        "player": "Zach Collins",
        "status": "OUT",
        "reason": "Right toe (sprain)",
        "date": "2026-01-14T23:29Z"
      },
      {
        "player": "Noa Essengue",
        "status": "OUT",
        "reason": "Left shoulder (surgery)",
        "date": "2025-12-03T23:24Z"
      }
    ],
    "CLE": [
      {
        "player": "Tyrese Proctor",
        "status": "QUESTIONABLE",
        "reason": "illness",
        "date": "2026-02-09T20:06Z"
      },
      {
        "player": "Jaylon Tyson",
        "status": "QUESTIONABLE",
        "reason": "Left ankle (sprain)",
        "date": "2026-02-08T23:37Z"
      },
      {
        "player": "Dean Wade",
        "status": "QUESTIONABLE",
        "reason": "Left ankle (sprain)",
        "date": "2026-02-08T23:37Z"
      },
      {
        "player": "Evan Mobley",
        "status": "OUT",
        "reason": "Left calf (strain)",
        "date": "2026-01-27T21:24Z"
      },
      {
        "player": "Max Strus",
        "status": "OUT",
        "reason": "Left foot (surgery)",
        "date": "2026-01-06T19:13Z"
      }
    ],
    "DAL": [
      {
        "player": "Klay Thompson",
        "status": "QUESTIONABLE",
        "reason": "rest",
        "date": "2026-02-09T23:47Z"
      },
      {
        "player": "Kyrie Irving",
        "status": "OUT",
        "reason": "Left knee (surgery)",
        "date": "2026-02-03T17:47Z"
      },
      {
        "player": "Dereck Lively II",
        "status": "OUT",
        "reason": "Right foot (surgery)",
        "date": "2025-12-21T18:06Z"
      }
    ],
    "DEN": [
      {
        "player": "Spencer Jones",
        "status": "OUT",
        "reason": "concussion",
        "date": "2026-02-08T22:30Z"
      },
      {
        "player": "Nikola Jokic",
        "status": "QUESTIONABLE",
        "reason": "Left ankle (sprain)",
        "date": "2026-02-08T22:28Z"
      },
      {
        "player": "Christian Braun",
        "status": "QUESTIONABLE",
        "reason": "Left ankle (sprain)",
        "date": "2026-02-08T22:26Z"
      },
      {
        "player": "Jamal Murray",
        "status": "QUESTIONABLE",
        "reason": "Left hip (inflammation)",
        "date": "2026-02-08T22:23Z"
      },
      {
        "player": "Peyton Watson",
        "status": "OUT",
        "reason": "Right hamstring (strain)",
        "date": "2026-02-06T17:58Z"
      },
      {
        "player": "Aaron Gordon",
        "status": "OUT",
        "reason": "Right hamstring (strain)",
        "date": "2026-01-29T21:43Z"
      },
      {
        "player": "Tamar Bates",
        "status": "OUT",
        "reason": "Left foot (surgery)",
        "date": "2025-12-22T22:53Z"
      }
    ],
    "DET": [
      {
        "player": "Ronald Holland II",
        "status": "OUT",
        "reason": "personal",
        "date": "2026-02-08T22:44Z"
      },
      {
        "player": "Tolu Smith",
        "status": "OUT",
        "reason": "calf",
        "date": "2026-02-04T14:36Z"
      }
    ],
    "GS": [
      {
        "player": "Will Richard",
        "status": "QUESTIONABLE",
        "reason": "Right knee (soreness)",
        "date": "2026-02-09T20:10Z"
      },
      {
        "player": "L.J. Cryer",
        "status": "OUT",
        "reason": "Left hamstring",
        "date": "2026-02-09T01:27Z"
      },
      {
        "player": "Stephen Curry",
        "status": "OUT",
        "reason": "Right knee (soreness)",
        "date": "2026-02-09T01:04Z"
      },
      {
        "player": "Kristaps Porzingis",
        "status": "OUT",
        "reason": "Left achilles",
        "date": "2026-02-08T00:13Z"
      },
      {
        "player": "Seth Curry",
        "status": "OUT",
        "reason": "Left back (pinched nerve)",
        "date": "2026-02-01T01:28Z"
      },
      {
        "player": "Jimmy Butler III",
        "status": "OUT",
        "reason": "Right knee (surgery)",
        "date": "2026-01-20T13:11Z"
      }
    ],
    "HOU": [
      {
        "player": "Steven Adams",
        "status": "OUT",
        "reason": "Left ankle (surgery)",
        "date": "2026-01-28T20:34Z"
      },
      {
        "player": "Fred VanVleet",
        "status": "OUT",
        "reason": "Right knee (surgery)",
        "date": "2025-09-22T20:02Z"
      }
    ],
    "IND": [
      {
        "player": "Ivica Zubac",
        "status": "QUESTIONABLE",
        "reason": "Left ankle (sprain)",
        "date": "2026-02-09T22:40Z"
      },
      {
        "player": "Aaron Nesmith",
        "status": "QUESTIONABLE",
        "reason": "Left hand",
        "date": "2026-02-09T22:39Z"
      },
      {
        "player": "Micah Potter",
        "status": "QUESTIONABLE",
        "reason": "Left hip (bruise)",
        "date": "2026-02-09T22:39Z"
      },
      {
        "player": "T.J. McConnell",
        "status": "QUESTIONABLE",
        "reason": "Right hamstring (soreness)",
        "date": "2026-02-09T22:37Z"
      },
      {
        "player": "Johnny Furphy",
        "status": "OUT",
        "reason": "Right knee (surgery)",
        "date": "2026-02-09T21:43Z"
      },
      {
        "player": "Ethan Thompson",
        "status": "QUESTIONABLE",
        "reason": "thumb",
        "date": "2026-02-09T04:12Z"
      },
      {
        "player": "Obi Toppin",
        "status": "OUT",
        "reason": "Right foot (surgery)",
        "date": "2026-01-31T22:28Z"
      },
      {
        "player": "Tyrese Haliburton",
        "status": "OUT",
        "reason": "Right achilles (surgery)",
        "date": "2026-01-27T14:58Z"
      }
    ],
    "LAC": [
      {
        "player": "Darius Garland",
        "status": "OUT",
        "reason": "Right toe (sprain)",
        "date": "2026-02-09T19:41Z"
      },
      {
        "player": "Bradley Beal",
        "status": "OUT",
        "reason": "Left hip (surgery)",
        "date": "2025-11-12T20:14Z"
      }
    ],
    "LAL": [
      {
        "player": "Adou Thiero",
        "status": "OUT",
        "reason": "Right knee (sprain)",
        "date": "2026-02-09T23:54Z"
      },
      {
        "player": "Dalton Knecht",
        "status": "QUESTIONABLE",
        "reason": "Right hamstring (soreness)",
        "date": "2026-02-09T22:55Z"
      },
      {
        "player": "Luka Doncic",
        "status": "OUT",
        "reason": "Left hamstring (strain)",
        "date": "2026-02-09T00:55Z"
      }
    ],
    "MEM": [
      {
        "player": "Walter Clayton Jr.",
        "status": "QUESTIONABLE",
        "reason": "Right calf (bruise)",
        "date": "2026-02-09T01:39Z"
      },
      {
        "player": "Santi Aldama",
        "status": "OUT",
        "reason": "Right knee",
        "date": "2026-02-09T01:33Z"
      },
      {
        "player": "Ja Morant",
        "status": "OUT",
        "reason": "Left elbow (sprain)",
        "date": "2026-01-24T16:07Z"
      },
      {
        "player": "Zach Edey",
        "status": "OUT",
        "reason": "Left ankle (fracture)",
        "date": "2026-01-14T15:12Z"
      },
      {
        "player": "Brandon Clarke",
        "status": "OUT",
        "reason": "Right calf (strain)",
        "date": "2026-01-14T15:12Z"
      }
    ],
    "MIA": [
      {
        "player": "Norman Powell",
        "status": "OUT",
        "reason": "back (soreness)",
        "date": "2026-02-09T22:48Z"
      },
      {
        "player": "Pelle Larsson",
        "status": "OUT",
        "reason": "Right elbow (bruise)",
        "date": "2026-02-09T22:47Z"
      },
      {
        "player": "Tyler Herro",
        "status": "OUT",
        "reason": "Right ribs (bruise)",
        "date": "2026-02-09T18:11Z"
      },
      {
        "player": "Terry Rozier",
        "status": "OUT",
        "reason": "",
        "date": "2025-10-23T16:24Z"
      }
    ],
    "MIL": [
      {
        "player": "Cam Thomas",
        "status": "QUESTIONABLE",
        "reason": "",
        "date": "2026-02-09T17:00Z"
      },
      {
        "player": "Giannis Antetokounmpo",
        "status": "OUT",
        "reason": "Right calf (strain)",
        "date": "2026-02-05T17:11Z"
      },
      {
        "player": "Taurean Prince",
        "status": "OUT",
        "reason": "neck (surgery)",
        "date": "2026-01-01T16:50Z"
      }
    ],
    "MIN": [
      {
        "player": "Terrence Shannon Jr.",
        "status": "OUT",
        "reason": "Left foot (strain)",
        "date": "2026-02-09T16:12Z"
      }
    ],
    "NO": [
      {
        "player": "Dejounte Murray",
        "status": "OUT",
        "reason": "Right achilles (surgery)",
        "date": "2026-02-08T21:49Z"
      }
    ],
    "NY": [
      {
        "player": "OG Anunoby",
        "status": "QUESTIONABLE",
        "reason": "Right toe (soreness)",
        "date": "2026-02-09T22:25Z"
      },
      {
        "player": "Mitchell Robinson",
        "status": "OUT",
        "reason": "Left ankle",
        "date": "2026-02-09T22:21Z"
      },
      {
        "player": "Miles McBride",
        "status": "OUT",
        "reason": "pelvis (surgery)",
        "date": "2026-02-05T18:04Z"
      }
    ],
    "OKC": [
      {
        "player": "Ajay Mitchell",
        "status": "OUT",
        "reason": "abdomen (strain)",
        "date": "2026-02-09T01:22Z"
      },
      {
        "player": "Nikola Topic",
        "status": "OUT",
        "reason": "illness (surgery)",
        "date": "2026-02-08T15:17Z"
      },
      {
        "player": "Shai Gilgeous-Alexander",
        "status": "OUT",
        "reason": "abdomen (strain)",
        "date": "2026-02-04T19:13Z"
      },
      {
        "player": "Thomas Sorber",
        "status": "OUT",
        "reason": "Right knee (surgery)",
        "date": "2025-09-05T21:43Z"
      }
    ],
    "ORL": [
      {
        "player": "Colin Castleton",
        "status": "OUT",
        "reason": "Left thumb (fracture)",
        "date": "2025-11-24T16:19Z"
      }
    ],
    "PHI": [
      {
        "player": "Quentin Grimes",
        "status": "QUESTIONABLE",
        "reason": "illness",
        "date": "2026-02-09T21:35Z"
      },
      {
        "player": "Joel Embiid",
        "status": "QUESTIONABLE",
        "reason": "Right knee",
        "date": "2026-02-09T01:15Z"
      },
      {
        "player": "Paul George",
        "status": "OUT",
        "reason": "suspension",
        "date": "2026-01-31T16:49Z"
      }
    ],
    "PHX": [
      {
        "player": "Isaiah Livers",
        "status": "OUT",
        "reason": "Left shoulder (sprain)",
        "date": "2026-02-08T00:30Z"
      },
      {
        "player": "Grayson Allen",
        "status": "OUT",
        "reason": "Right knee (sprain)",
        "date": "2026-02-08T00:26Z"
      },
      {
        "player": "Cole Anthony",
        "status": "QUESTIONABLE",
        "reason": "not with team",
        "date": "2026-02-07T20:20Z"
      }
    ],
    "POR": [
      {
        "player": "Scoot Henderson",
        "status": "QUESTIONABLE",
        "reason": "Left hamstring",
        "date": "2026-02-09T01:24Z"
      },
      {
        "player": "Robert Williams III",
        "status": "QUESTIONABLE",
        "reason": "Left knee",
        "date": "2026-02-09T01:18Z"
      },
      {
        "player": "Deni Avdija",
        "status": "QUESTIONABLE",
        "reason": "back (strain)",
        "date": "2026-02-09T01:14Z"
      },
      {
        "player": "Shaedon Sharpe",
        "status": "OUT",
        "reason": "Left calf (soreness)",
        "date": "2026-02-09T01:09Z"
      },
      {
        "player": "Kris Murray",
        "status": "OUT",
        "reason": "back (strain)",
        "date": "2026-02-09T01:06Z"
      },
      {
        "player": "Matisse Thybulle",
        "status": "OUT",
        "reason": "Right knee (tendinitis)",
        "date": "2026-02-01T01:12Z"
      },
      {
        "player": "Damian Lillard",
        "status": "OUT",
        "reason": "Left achilles (surgery)",
        "date": "2025-09-25T16:32Z"
      }
    ],
    "SAC": [
      {
        "player": "Domantas Sabonis",
        "status": "OUT",
        "reason": "back (inflammation)",
        "date": "2026-02-09T19:20Z"
      },
      {
        "player": "Zach LaVine",
        "status": "OUT",
        "reason": "Right finger (soreness)",
        "date": "2026-02-08T23:22Z"
      },
      {
        "player": "Malik Monk",
        "status": "OUT",
        "reason": "illness",
        "date": "2026-02-08T23:20Z"
      },
      {
        "player": "De'Andre Hunter",
        "status": "OUT",
        "reason": "Left eye (inflammation)",
        "date": "2026-02-08T23:05Z"
      },
      {
        "player": "Keegan Murray",
        "status": "OUT",
        "reason": "Left ankle (sprain)",
        "date": "2026-02-03T21:29Z"
      }
    ],
    "SA": [
      {
        "player": "Lindy Waters III",
        "status": "OUT",
        "reason": "Left knee (soreness)",
        "date": "2026-02-06T23:36Z"
      },
      {
        "player": "David Jones Garcia",
        "status": "OUT",
        "reason": "Right ankle (surgery)",
        "date": "2026-02-04T22:39Z"
      }
    ],
    "TOR": [
      {
        "player": "Collin Murray-Boyles",
        "status": "QUESTIONABLE",
        "reason": "Left thumb",
        "date": "2026-02-08T21:00Z"
      },
      {
        "player": "Jakob Poeltl",
        "status": "QUESTIONABLE",
        "reason": "back (strain)",
        "date": "2026-02-08T18:25Z"
      },
      {
        "player": "Chucky Hepburn",
        "status": "OUT",
        "reason": "Right knee (surgery)",
        "date": "2026-01-06T16:34Z"
      }
    ],
    "UTAH": [
      {
        "player": "Kevin Love",
        "status": "OUT",
        "reason": "rest",
        "date": "2026-02-09T16:16Z"
      },
      {
        "player": "Keyonte George",
        "status": "OUT",
        "reason": "Right ankle (sprain)",
        "date": "2026-02-08T22:39Z"
      },
      {
        "player": "Elijah Harkless",
        "status": "OUT",
        "reason": "Left hamstring (strain)",
        "date": "2026-01-31T03:17Z"
      },
      {
        "player": "Walker Kessler",
        "status": "OUT",
        "reason": "Left shoulder (surgery)",
        "date": "2025-11-05T18:51Z"
      }
    ],
    "WSH": [
      {
        "player": "Anthony Gill",
        "status": "QUESTIONABLE",
        "reason": "Right hand (bruise)",
        "date": "2026-02-09T14:30Z"
      },
      {
        "player": "D'Angelo Russell",
        "status": "OUT",
        "reason": "",
        "date": "2026-02-08T21:44Z"
      },
      {
        "player": "Kyshawn George",
        "status": "QUESTIONABLE",
        "reason": "Left ankle (sprain)",
        "date": "2026-02-08T20:55Z"
      },
      {
        "player": "Jaden Hardy",
        "status": "QUESTIONABLE",
        "reason": "rest",
        "date": "2026-02-08T15:31Z"
      },
      {
        "player": "Tre Johnson",
        "status": "QUESTIONABLE",
        "reason": "Left ankle (sprain)",
        "date": "2026-02-08T15:14Z"
      },
      {
        "player": "Anthony Davis",
        "status": "OUT",
        "reason": "Left finger (sprain)",
        "date": "2026-02-07T04:58Z"
      },
      {
        "player": "Cam Whitmore",
        "status": "OUT",
        "reason": "Right shoulder",
        "date": "2026-01-15T22:15Z"
      },
      {
        "player": "Trae Young",
        "status": "OUT",
        "reason": "Right knee (sprain)",
        "date": "2026-01-14T20:58Z"
      }
    ]
  }
}