{
  "date": "2026-03-04",
  "sport": "NBA",
  "type": "game",
  "locked_at": "2026-03-04T08:54:44",
  "recommendations": [
    {
      "bet_type": "SPREAD",
      "game": "OKC @ NYK",
      "away_team": "OKC",
      "home_team": "NYK",
      "pick": "NYK +4.5",
      "confidence": 76.0,
      "commence_time": "2026-03-05T00:10:00Z",
      "reasons": ["76.0% confidence", "High confidence"],
      "rec_rank": 1
    },
    {
      "bet_type": "ML",
      "game": "IND @ LAC",
      "away_team": "IND",
      "home_team": "LAC",
      "pick": "LAC",
      "confidence": 69.9,
      "commence_time": "2026-03-05T03:40:00Z",
      "reasons": ["69.9% confidence"],
      "rec_rank": 2
    },
    {
      "bet_type": "SPREAD",
      "game": "POR @ MEM",
      "away_team": "POR",
      "home_team": "MEM",
      "pick": "MEM +7.5",
      "confidence": 69.7,
      "commence_time": "2026-03-05T01:10:00Z",
      "reasons": ["69.7% confidence"],
      "rec_rank": 3
    },
    {
      "bet_type": "SPREAD",
      "game": "ATL @ MIL",
      "away_team": "ATL",
      "home_team": "MIL",
      "pick": "ATL +1.0",
      "confidence": 68.2,
      "commence_time": "2026-03-05T02:40:00Z",
      "reasons": ["68.2% confidence"],
      "rec_rank": 4
    },
    {
      "bet_type": "ML",
      "game": "ATL @ MIL",
      "away_team": "ATL",
      "home_team": "MIL",
      "pick": "ATL",
      "confidence": 66.2,
      "commence_time": "2026-03-05T02:40:00Z",
      "reasons": ["66.2% confidence"],
      "rec_rank": 5
    }
  ]
}
