{
  "date": "2026-01-31",
  "sport": "NBA",
  "updated": "2026-01-31T18:51:50",
  "projections": [
    {
      "player": "Bennedict Mathurin",
      "team": "IND",
      "prop": "PTS",
      "direction": "UNDER",
      "line": 16.5,
      "projection": 14.6,
      "confidence": 52.0,
      "ev": -4.7,
      "diff": -1.9,
      "market_odds": -120,
      "fair_odds": -108,
      "prob_edge": -2.5
    },
    {
      "player": "Bennedict Mathurin",
      "team": "IND",
      "prop": "REB",
      "direction": "UNDER",
      "line": 5.5,
      "projection": 5.2,
      "confidence": 49.0,
      "ev": -20.0,
      "diff": -0.3,
      "market_odds": -158,
      "fair_odds": 104,
      "prob_edge": -12.2
    },
    {
      "player": "Bennedict Mathurin",
      "team": "IND",
      "prop": "PRA",
      "direction": "UNDER",
      "line": 23.5,
      "projection": 22.0,
      "confidence": 50.6,
      "ev": -3.8,
      "diff": -1.5,
      "market_odds": -111,
      "fair_odds": -102,
      "prob_edge": -2.0
    },
    {
      "player": "Andrew Nembhard",
      "team": "IND",
      "prop": "PTS",
      "direction": "OVER",
      "line": 16.5,
      "projection": 17.1,
      "confidence": 49.9,
      "ev": -9.2,
      "diff": 0.6,
      "market_odds": -122,
      "fair_odds": 100,
      "prob_edge": -5.1
    },
    {
      "player": "Andrew Nembhard",
      "team": "IND",
      "prop": "AST",
      "direction": "OVER",
      "line": 8.0,
      "projection": 8.6,
      "confidence": 50.4,
      "ev": -5.1,
      "diff": 0.6,
      "market_odds": -113,
      "fair_odds": -102,
      "prob_edge": -2.7
    },
    {
      "player": "Andrew Nembhard",
      "team": "IND",
      "prop": "PRA",
      "direction": "UNDER",
      "line": 29.0,
      "projection": 28.6,
      "confidence": 51.7,
      "ev": -4.5,
      "diff": -0.4,
      "market_odds": -118,
      "fair_odds": -107,
      "prob_edge": -2.4
    },
    {
      "player": "Aaron Nesmith",
      "team": "IND",
      "prop": "REB",
      "direction": "UNDER",
      "line": 5.5,
      "projection": 5.0,
      "confidence": 52.8,
      "ev": -11.4,
      "diff": -0.5,
      "market_odds": -147,
      "fair_odds": -112,
      "prob_edge": -6.7
    },
    {
      "player": "Pascal Siakam",
      "team": "IND",
      "prop": "PTS",
      "direction": "UNDER",
      "line": 24.5,
      "projection": 23.7,
      "confidence": 50.9,
      "ev": -7.4,
      "diff": -0.8,
      "market_odds": -122,
      "fair_odds": -104,
      "prob_edge": -4.1
    },
    {
      "player": "Pascal Siakam",
      "team": "IND",
      "prop": "REB",
      "direction": "UNDER",
      "line": 7.5,
      "projection": 7.0,
      "confidence": 53.3,
      "ev": -6.0,
      "diff": -0.5,
      "market_odds": -131,
      "fair_odds": -114,
      "prob_edge": -3.4
    },
    {
      "player": "Pascal Siakam",
      "team": "IND",
      "prop": "AST",
      "direction": "OVER",
      "line": 4.0,
      "projection": 4.6,
      "confidence": 50.3,
      "ev": -4.0,
      "diff": 0.6,
      "market_odds": -110,
      "fair_odds": -101,
      "prob_edge": -2.1
    },
    {
      "player": "Pascal Siakam",
      "team": "IND",
      "prop": "PRA",
      "direction": "UNDER",
      "line": 36.0,
      "projection": 35.5,
      "confidence": 50.8,
      "ev": -5.3,
      "diff": -0.5,
      "market_odds": -116,
      "fair_odds": -103,
      "prob_edge": -2.9
    },
    {
      "player": "Jalen Johnson",
      "team": "ATL",
      "prop": "PTS",
      "direction": "UNDER",
      "line": 23.5,
      "projection": 19.8,
      "confidence": 54.6,
      "ev": 2.5,
      "diff": -3.7,
      "market_odds": -114,
      "fair_odds": -120,
      "prob_edge": 1.3,
      "edge": "GOOD"
    },
    {
      "player": "Jalen Johnson",
      "team": "ATL",
      "prop": "REB",
      "direction": "OVER",
      "line": 10.5,
      "projection": 10.9,
      "confidence": 48.0,
      "ev": -3.0,
      "diff": 0.4,
      "market_odds": 102,
      "fair_odds": 108,
      "prob_edge": -1.5
    },
    {
      "player": "Jalen Johnson",
      "team": "ATL",
      "prop": "AST",
      "direction": "OVER",
      "line": 7.5,
      "projection": 7.5,
      "confidence": 48.1,
      "ev": 1.6,
      "diff": 0.0,
      "market_odds": 111,
      "fair_odds": 108,
      "prob_edge": 0.7,
      "edge": "LEAN"
    },
    {
      "player": "Jalen Johnson",
      "team": "ATL",
      "prop": "PRA",
      "direction": "UNDER",
      "line": 41.5,
      "projection": 39.2,
      "confidence": 56.4,
      "ev": 5.9,
      "diff": -2.3,
      "market_odds": -114,
      "fair_odds": -129,
      "prob_edge": 3.1,
      "edge": "STRONG"
    },
    {
      "player": "Dyson Daniels",
      "team": "ATL",
      "prop": "REB",
      "direction": "UNDER",
      "line": 6.5,
      "projection": 6.1,
      "confidence": 50.3,
      "ev": -7.5,
      "diff": -0.4,
      "market_odds": -119,
      "fair_odds": -101,
      "prob_edge": -4.0
    },
    {
      "player": "Dyson Daniels",
      "team": "ATL",
      "prop": "AST",
      "direction": "OVER",
      "line": 6.5,
      "projection": 7.0,
      "confidence": 51.6,
      "ev": -5.3,
      "diff": 0.5,
      "market_odds": -120,
      "fair_odds": -107,
      "prob_edge": -2.9
    },
    {
      "player": "Dyson Daniels",
      "team": "ATL",
      "prop": "PRA",
      "direction": "UNDER",
      "line": 26.0,
      "projection": 25.1,
      "confidence": 49.2,
      "ev": -7.2,
      "diff": -0.9,
      "market_odds": -113,
      "fair_odds": 103,
      "prob_edge": -3.9
    },
    {
      "player": "Nickeil Alexander-Walker",
      "team": "ATL",
      "prop": "PTS",
      "direction": "UNDER",
      "line": 19.5,
      "projection": 18.8,
      "confidence": 49.7,
      "ev": -8.2,
      "diff": -0.7,
      "market_odds": -118,
      "fair_odds": 101,
      "prob_edge": -4.4
    },
    {
      "player": "Nickeil Alexander-Walker",
      "team": "ATL",
      "prop": "AST",
      "direction": "OVER",
      "line": 3.5,
      "projection": 4.0,
      "confidence": 51.9,
      "ev": 12.2,
      "diff": 0.5,
      "market_odds": 116,
      "fair_odds": -108,
      "prob_edge": 5.6,
      "edge": "STRONG"
    },
    {
      "player": "Nickeil Alexander-Walker",
      "team": "ATL",
      "prop": "PRA",
      "direction": "UNDER",
      "line": 27.0,
      "projection": 25.7,
      "confidence": 49.2,
      "ev": -10.5,
      "diff": -1.3,
      "market_odds": -122,
      "fair_odds": 103,
      "prob_edge": -5.8
    },
    {
      "player": "Tyrese Maxey",
      "team": "PHI",
      "prop": "PTS",
      "direction": "UNDER",
      "line": 27.5,
      "projection": 26.4,
      "confidence": 49.3,
      "ev": -9.0,
      "diff": -1.1,
      "market_odds": -118,
      "fair_odds": 103,
      "prob_edge": -4.8
    },
    {
      "player": "Tyrese Maxey",
      "team": "PHI",
      "prop": "AST",
      "direction": "OVER",
      "line": 7.5,
      "projection": 8.0,
      "confidence": 49.7,
      "ev": 5.8,
      "diff": 0.5,
      "market_odds": 113,
      "fair_odds": 101,
      "prob_edge": 2.8,
      "edge": "STRONG"
    },
    {
      "player": "Tyrese Maxey",
      "team": "PHI",
      "prop": "PRA",
      "direction": "UNDER",
      "line": 38.5,
      "projection": 37.6,
      "confidence": 48.7,
      "ev": -8.2,
      "diff": -0.9,
      "market_odds": -113,
      "fair_odds": 105,
      "prob_edge": -4.4
    },
    {
      "player": "Joel Embiid",
      "team": "PHI",
      "prop": "PTS",
      "direction": "UNDER",
      "line": 29.5,
      "projection": 29.1,
      "confidence": 51.8,
      "ev": -0.2,
      "diff": -0.4,
      "market_odds": -108,
      "fair_odds": -107,
      "prob_edge": -0.1
    },
    {
      "player": "Joel Embiid",
      "team": "PHI",
      "prop": "REB",
      "direction": "UNDER",
      "line": 9.5,
      "projection": 8.0,
      "confidence": 56.0,
      "ev": -2.5,
      "diff": -1.5,
      "market_odds": -135,
      "fair_odds": -127,
      "prob_edge": -1.4
    },
    {
      "player": "Joel Embiid",
      "team": "PHI",
      "prop": "AST",
      "direction": "OVER",
      "line": 4.5,
      "projection": 5.4,
      "confidence": 53.5,
      "ev": -6.6,
      "diff": 0.9,
      "market_odds": -134,
      "fair_odds": -115,
      "prob_edge": -3.8
    },
    {
      "player": "Joel Embiid",
      "team": "PHI",
      "prop": "PRA",
      "direction": "UNDER",
      "line": 44.0,
      "projection": 42.7,
      "confidence": 53.6,
      "ev": 1.6,
      "diff": -1.3,
      "market_odds": -112,
      "fair_odds": -116,
      "prob_edge": 0.8,
      "edge": "LEAN"
    },
    {
      "player": "VJ Edgecombe",
      "team": "PHI",
      "prop": "PTS",
      "direction": "UNDER",
      "line": 14.0,
      "projection": 12.4,
      "confidence": 49.2,
      "ev": -8.3,
      "diff": -1.6,
      "market_odds": -116,
      "fair_odds": 103,
      "prob_edge": -4.5
    },
    {
      "player": "VJ Edgecombe",
      "team": "PHI",
      "prop": "REB",
      "direction": "UNDER",
      "line": 5.5,
      "projection": 5.0,
      "confidence": 49.5,
      "ev": -18.7,
      "diff": -0.5,
      "market_odds": -156,
      "fair_odds": 102,
      "prob_edge": -11.4
    },
    {
      "player": "VJ Edgecombe",
      "team": "PHI",
      "prop": "AST",
      "direction": "OVER",
      "line": 4.5,
      "projection": 4.8,
      "confidence": 51.8,
      "ev": 10.4,
      "diff": 0.3,
      "market_odds": 113,
      "fair_odds": -107,
      "prob_edge": 4.9,
      "edge": "STRONG"
    },
    {
      "player": "VJ Edgecombe",
      "team": "PHI",
      "prop": "PRA",
      "direction": "UNDER",
      "line": 23.5,
      "projection": 22.1,
      "confidence": 48.3,
      "ev": -7.8,
      "diff": -1.4,
      "market_odds": -110,
      "fair_odds": 107,
      "prob_edge": -4.1
    },
    {
      "player": "Zion Williamson",
      "team": "NOP",
      "prop": "PTS",
      "direction": "UNDER",
      "line": 21.5,
      "projection": 20.4,
      "confidence": 49.2,
      "ev": -6.1,
      "diff": -1.1,
      "market_odds": -110,
      "fair_odds": 103,
      "prob_edge": -3.2
    },
    {
      "player": "Zion Williamson",
      "team": "NOP",
      "prop": "REB",
      "direction": "OVER",
      "line": 6.5,
      "projection": 6.7,
      "confidence": 50.5,
      "ev": 7.1,
      "diff": 0.2,
      "market_odds": 112,
      "fair_odds": -102,
      "prob_edge": 3.3,
      "edge": "STRONG"
    },
    {
      "player": "Zion Williamson",
      "team": "NOP",
      "prop": "AST",
      "direction": "OVER",
      "line": 3.5,
      "projection": 3.8,
      "confidence": 50.7,
      "ev": -10.6,
      "diff": 0.3,
      "market_odds": -131,
      "fair_odds": -103,
      "prob_edge": -6.0
    },
    {
      "player": "Zion Williamson",
      "team": "NOP",
      "prop": "PRA",
      "direction": "UNDER",
      "line": 32.0,
      "projection": 30.5,
      "confidence": 50.9,
      "ev": -5.3,
      "diff": -1.5,
      "market_odds": -116,
      "fair_odds": -104,
      "prob_edge": -2.8
    },
    {
      "player": "Derik Queen",
      "team": "NOP",
      "prop": "REB",
      "direction": "OVER",
      "line": 6.5,
      "projection": 7.0,
      "confidence": 56.0,
      "ev": -4.8,
      "diff": 0.5,
      "market_odds": -143,
      "fair_odds": -127,
      "prob_edge": -2.8
    },
    {
      "player": "Derik Queen",
      "team": "NOP",
      "prop": "AST",
      "direction": "OVER",
      "line": 4.5,
      "projection": 4.8,
      "confidence": 53.5,
      "ev": 12.5,
      "diff": 0.3,
      "market_odds": 110,
      "fair_odds": -115,
      "prob_edge": 5.9,
      "edge": "STRONG"
    },
    {
      "player": "Trey Murphy III",
      "team": "NOP",
      "prop": "PTS",
      "direction": "UNDER",
      "line": 20.5,
      "projection": 19.5,
      "confidence": 49.9,
      "ev": -3.5,
      "diff": -1.0,
      "market_odds": -107,
      "fair_odds": 100,
      "prob_edge": -1.8
    },
    {
      "player": "Trey Murphy III",
      "team": "NOP",
      "prop": "REB",
      "direction": "UNDER",
      "line": 5.5,
      "projection": 4.5,
      "confidence": 52.8,
      "ev": -12.5,
      "diff": -1.0,
      "market_odds": -152,
      "fair_odds": -112,
      "prob_edge": -7.5
    },
    {
      "player": "Trey Murphy III",
      "team": "NOP",
      "prop": "AST",
      "direction": "OVER",
      "line": 3.5,
      "projection": 4.0,
      "confidence": 51.0,
      "ev": -13.8,
      "diff": 0.5,
      "market_odds": -145,
      "fair_odds": -104,
      "prob_edge": -8.2
    },
    {
      "player": "Trey Murphy III",
      "team": "NOP",
      "prop": "PRA",
      "direction": "UNDER",
      "line": 30.0,
      "projection": 27.9,
      "confidence": 51.2,
      "ev": -2.3,
      "diff": -2.1,
      "market_odds": -110,
      "fair_odds": -105,
      "prob_edge": -1.2
    },
    {
      "player": "Saddiq Bey",
      "team": "NOP",
      "prop": "PTS",
      "direction": "OVER",
      "line": 15.5,
      "projection": 20.1,
      "confidence": 54.0,
      "ev": -1.3,
      "diff": 4.6,
      "market_odds": -121,
      "fair_odds": -117,
      "prob_edge": -0.8
    },
    {
      "player": "Saddiq Bey",
      "team": "NOP",
      "prop": "REB",
      "direction": "OVER",
      "line": 6.0,
      "projection": 6.0,
      "confidence": 51.0,
      "ev": 1.1,
      "diff": 0.0,
      "market_odds": -102,
      "fair_odds": -104,
      "prob_edge": 0.5,
      "edge": "LEAN"
    },
    {
      "player": "Saddiq Bey",
      "team": "NOP",
      "prop": "PRA",
      "direction": "OVER",
      "line": 24.5,
      "projection": 29.5,
      "confidence": 53.4,
      "ev": 3.8,
      "diff": 5.0,
      "market_odds": -106,
      "fair_odds": -115,
      "prob_edge": 1.9,
      "edge": "GOOD"
    },
    {
      "player": "Bam Adebayo",
      "team": "MIA",
      "prop": "PTS",
      "direction": "UNDER",
      "line": 21.5,
      "projection": 21.0,
      "confidence": 53.0,
      "ev": -4.6,
      "diff": -0.5,
      "market_odds": -125,
      "fair_odds": -113,
      "prob_edge": -2.6
    },
    {
      "player": "Bam Adebayo",
      "team": "MIA",
      "prop": "REB",
      "direction": "UNDER",
      "line": 10.5,
      "projection": 10.4,
      "confidence": 51.6,
      "ev": -8.7,
      "diff": -0.1,
      "market_odds": -130,
      "fair_odds": -107,
      "prob_edge": -4.9
    },
    {
      "player": "Bam Adebayo",
      "team": "MIA",
      "prop": "AST",
      "direction": "OVER",
      "line": 3.5,
      "projection": 3.5,
      "confidence": 48.6,
      "ev": 10.3,
      "diff": 0.0,
      "market_odds": 127,
      "fair_odds": 106,
      "prob_edge": 4.5,
      "edge": "STRONG"
    },
    {
      "player": "Bam Adebayo",
      "team": "MIA",
      "prop": "PRA",
      "direction": "UNDER",
      "line": 35.0,
      "projection": 34.4,
      "confidence": 53.3,
      "ev": -1.9,
      "diff": -0.6,
      "market_odds": -119,
      "fair_odds": -114,
      "prob_edge": -1.0
    },
    {
      "player": "Andrew Wiggins",
      "team": "MIA",
      "prop": "PTS",
      "direction": "UNDER",
      "line": 17.5,
      "projection": 13.9,
      "confidence": 53.1,
      "ev": 1.0,
      "diff": -3.6,
      "market_odds": -111,
      "fair_odds": -113,
      "prob_edge": 0.5,
      "edge": "LEAN"
    },
    {
      "player": "Andrew Wiggins",
      "team": "MIA",
      "prop": "REB",
      "direction": "UNDER",
      "line": 5.5,
      "projection": 5.3,
      "confidence": 52.8,
      "ev": -13.2,
      "diff": -0.2,
      "market_odds": -155,
      "fair_odds": -112,
      "prob_edge": -8.0
    },
    {
      "player": "Andrew Wiggins",
      "team": "MIA",
      "prop": "AST",
      "direction": "OVER",
      "line": 3.0,
      "projection": 3.2,
      "confidence": 50.4,
      "ev": -4.9,
      "diff": 0.2,
      "market_odds": -113,
      "fair_odds": -102,
      "prob_edge": -2.7
    },
    {
      "player": "Andrew Wiggins",
      "team": "MIA",
      "prop": "PRA",
      "direction": "UNDER",
      "line": 26.0,
      "projection": 22.4,
      "confidence": 53.0,
      "ev": -0.1,
      "diff": -3.6,
      "market_odds": -113,
      "fair_odds": -113,
      "prob_edge": -0.1
    },
    {
      "player": "Ayo Dosunmu",
      "team": "CHI",
      "prop": "PTS",
      "direction": "UNDER",
      "line": 19.0,
      "projection": 16.9,
      "confidence": 48.8,
      "ev": -6.5,
      "diff": -2.1,
      "market_odds": -109,
      "fair_odds": 105,
      "prob_edge": -3.4
    },
    {
      "player": "Ayo Dosunmu",
      "team": "CHI",
      "prop": "REB",
      "direction": "UNDER",
      "line": 4.5,
      "projection": 3.5,
      "confidence": 52.4,
      "ev": -13.9,
      "diff": -1.0,
      "market_odds": -156,
      "fair_odds": -110,
      "prob_edge": -8.5
    },
    {
      "player": "Ayo Dosunmu",
      "team": "CHI",
      "prop": "AST",
      "direction": "UNDER",
      "line": 6.5,
      "projection": 4.1,
      "confidence": 56.9,
      "ev": -6.7,
      "diff": -2.4,
      "market_odds": -156,
      "fair_odds": -132,
      "prob_edge": -4.0
    },
    {
      "player": "Ayo Dosunmu",
      "team": "CHI",
      "prop": "PRA",
      "direction": "UNDER",
      "line": 30.0,
      "projection": 24.3,
      "confidence": 50.8,
      "ev": -5.3,
      "diff": -5.7,
      "market_odds": -116,
      "fair_odds": -103,
      "prob_edge": -2.9
    },
    {
      "player": "Matas Buzelis",
      "team": "CHI",
      "prop": "PTS",
      "direction": "UNDER",
      "line": 20.5,
      "projection": 14.9,
      "confidence": 54.4,
      "ev": -3.1,
      "diff": -5.6,
      "market_odds": -128,
      "fair_odds": -119,
      "prob_edge": -1.7
    },
    {
      "player": "Matas Buzelis",
      "team": "CHI",
      "prop": "REB",
      "direction": "UNDER",
      "line": 7.5,
      "projection": 6.3,
      "confidence": 53.7,
      "ev": -6.5,
      "diff": -1.2,
      "market_odds": -135,
      "fair_odds": -116,
      "prob_edge": -3.7
    },
    {
      "player": "Matas Buzelis",
      "team": "CHI",
      "prop": "AST",
      "direction": "OVER",
      "line": 3.0,
      "projection": 3.5,
      "confidence": 50.2,
      "ev": -5.0,
      "diff": 0.5,
      "market_odds": -112,
      "fair_odds": -101,
      "prob_edge": -2.6
    },
    {
      "player": "Matas Buzelis",
      "team": "CHI",
      "prop": "PRA",
      "direction": "UNDER",
      "line": 30.5,
      "projection": 24.7,
      "confidence": 54.1,
      "ev": 2.9,
      "diff": -5.8,
      "market_odds": -111,
      "fair_odds": -118,
      "prob_edge": 1.5,
      "edge": "GOOD"
    },
    {
      "player": "Cedric Coward",
      "team": "MEM",
      "prop": "PTS",
      "direction": "OVER",
      "line": 14.5,
      "projection": 14.7,
      "confidence": 51.8,
      "ev": -1.4,
      "diff": 0.2,
      "market_odds": -111,
      "fair_odds": -107,
      "prob_edge": -0.8
    },
    {
      "player": "Cedric Coward",
      "team": "MEM",
      "prop": "REB",
      "direction": "UNDER",
      "line": 6.5,
      "projection": 6.1,
      "confidence": 44.7,
      "ev": -16.7,
      "diff": -0.4,
      "market_odds": -116,
      "fair_odds": 124,
      "prob_edge": -9.0
    },
    {
      "player": "Cedric Coward",
      "team": "MEM",
      "prop": "AST",
      "direction": "OVER",
      "line": 3.0,
      "projection": 3.2,
      "confidence": 52.8,
      "ev": 0.8,
      "diff": 0.2,
      "market_odds": -110,
      "fair_odds": -112,
      "prob_edge": 0.4,
      "edge": "LEAN"
    },
    {
      "player": "Cedric Coward",
      "team": "MEM",
      "prop": "PRA",
      "direction": "UNDER",
      "line": 24.5,
      "projection": 23.4,
      "confidence": 48.1,
      "ev": -10.0,
      "diff": -1.1,
      "market_odds": -115,
      "fair_odds": 108,
      "prob_edge": -5.4
    },
    {
      "player": "Donte DiVincenzo",
      "team": "MIN",
      "prop": "REB",
      "direction": "UNDER",
      "line": 4.5,
      "projection": 4.3,
      "confidence": 50.6,
      "ev": -9.6,
      "diff": -0.2,
      "market_odds": -127,
      "fair_odds": -102,
      "prob_edge": -5.3
    },
    {
      "player": "Donte DiVincenzo",
      "team": "MIN",
      "prop": "AST",
      "direction": "OVER",
      "line": 4.5,
      "projection": 4.7,
      "confidence": 49.6,
      "ev": 8.1,
      "diff": 0.2,
      "market_odds": 118,
      "fair_odds": 102,
      "prob_edge": 3.7,
      "edge": "STRONG"
    },
    {
      "player": "Donte DiVincenzo",
      "team": "MIN",
      "prop": "PRA",
      "direction": "UNDER",
      "line": 22.0,
      "projection": 21.4,
      "confidence": 51.0,
      "ev": -2.5,
      "diff": -0.6,
      "market_odds": -110,
      "fair_odds": -104,
      "prob_edge": -1.4
    },
    {
      "player": "Jaden McDaniels",
      "team": "MIN",
      "prop": "PTS",
      "direction": "OVER",
      "line": 14.0,
      "projection": 14.8,
      "confidence": 53.0,
      "ev": 1.6,
      "diff": 0.8,
      "market_odds": -109,
      "fair_odds": -113,
      "prob_edge": 0.8,
      "edge": "LEAN"
    },
    {
      "player": "Jaden McDaniels",
      "team": "MIN",
      "prop": "REB",
      "direction": "UNDER",
      "line": 4.5,
      "projection": 4.0,
      "confidence": 52.0,
      "ev": -7.4,
      "diff": -0.5,
      "market_odds": -128,
      "fair_odds": -108,
      "prob_edge": -4.1
    },
    {
      "player": "Anthony Edwards",
      "team": "MIN",
      "prop": "PTS",
      "direction": "OVER",
      "line": 28.0,
      "projection": 29.5,
      "confidence": 53.9,
      "ev": 0.9,
      "diff": 1.5,
      "market_odds": -115,
      "fair_odds": -117,
      "prob_edge": 0.4,
      "edge": "LEAN"
    },
    {
      "player": "Anthony Edwards",
      "team": "MIN",
      "prop": "REB",
      "direction": "OVER",
      "line": 5.5,
      "projection": 5.6,
      "confidence": 50.8,
      "ev": -10.7,
      "diff": 0.1,
      "market_odds": -132,
      "fair_odds": -103,
      "prob_edge": -6.1
    },
    {
      "player": "Anthony Edwards",
      "team": "MIN",
      "prop": "AST",
      "direction": "UNDER",
      "line": 4.5,
      "projection": 4.5,
      "confidence": 52.7,
      "ev": -16.0,
      "diff": -0.0,
      "market_odds": -168,
      "fair_odds": -111,
      "prob_edge": -10.0
    },
    {
      "player": "Anthony Edwards",
      "team": "MIN",
      "prop": "PRA",
      "direction": "OVER",
      "line": 38.5,
      "projection": 39.0,
      "confidence": 50.9,
      "ev": -3.2,
      "diff": 0.5,
      "market_odds": -111,
      "fair_odds": -104,
      "prob_edge": -1.7
    },
    {
      "player": "Naz Reid",
      "team": "MIN",
      "prop": "REB",
      "direction": "OVER",
      "line": 6.5,
      "projection": 7.2,
      "confidence": 56.4,
      "ev": 12.8,
      "diff": 0.7,
      "market_odds": -100,
      "fair_odds": -129,
      "prob_edge": 6.4,
      "edge": "STRONG"
    },
    {
      "player": "Naz Reid",
      "team": "MIN",
      "prop": "PRA",
      "direction": "OVER",
      "line": 22.5,
      "projection": 25.3,
      "confidence": 52.3,
      "ev": -5.2,
      "diff": 2.8,
      "market_odds": -123,
      "fair_odds": -110,
      "prob_edge": -2.9
    },
    {
      "player": "Rudy Gobert",
      "team": "MIN",
      "prop": "REB",
      "direction": "UNDER",
      "line": 11.5,
      "projection": 10.7,
      "confidence": 52.2,
      "ev": -6.7,
      "diff": -0.8,
      "market_odds": -127,
      "fair_odds": -109,
      "prob_edge": -3.7
    },
    {
      "player": "Rudy Gobert",
      "team": "MIN",
      "prop": "PRA",
      "direction": "UNDER",
      "line": 23.5,
      "projection": 22.4,
      "confidence": 49.6,
      "ev": -3.1,
      "diff": -1.1,
      "market_odds": -105,
      "fair_odds": 102,
      "prob_edge": -1.6
    },
    {
      "player": "Julius Randle",
      "team": "MIN",
      "prop": "PTS",
      "direction": "OVER",
      "line": 20.5,
      "projection": 22.3,
      "confidence": 54.1,
      "ev": -1.6,
      "diff": 1.8,
      "market_odds": -122,
      "fair_odds": -118,
      "prob_edge": -0.9
    },
    {
      "player": "Julius Randle",
      "team": "MIN",
      "prop": "REB",
      "direction": "UNDER",
      "line": 6.5,
      "projection": 6.4,
      "confidence": 49.1,
      "ev": -7.9,
      "diff": -0.1,
      "market_odds": -114,
      "fair_odds": 104,
      "prob_edge": -4.2
    },
    {
      "player": "Julius Randle",
      "team": "MIN",
      "prop": "AST",
      "direction": "OVER",
      "line": 4.5,
      "projection": 4.6,
      "confidence": 50.5,
      "ev": -16.9,
      "diff": 0.1,
      "market_odds": -155,
      "fair_odds": -102,
      "prob_edge": -10.3
    },
    {
      "player": "Julius Randle",
      "team": "MIN",
      "prop": "PRA",
      "direction": "UNDER",
      "line": 32.5,
      "projection": 31.7,
      "confidence": 51.5,
      "ev": -1.2,
      "diff": -0.8,
      "market_odds": -109,
      "fair_odds": -106,
      "prob_edge": -0.7
    },
    {
      "player": "Amen Thompson",
      "team": "HOU",
      "prop": "PTS",
      "direction": "UNDER",
      "line": 17.5,
      "projection": 16.1,
      "confidence": 50.3,
      "ev": -8.1,
      "diff": -1.4,
      "market_odds": -121,
      "fair_odds": -101,
      "prob_edge": -4.5
    },
    {
      "player": "Amen Thompson",
      "team": "HOU",
      "prop": "REB",
      "direction": "UNDER",
      "line": 7.5,
      "projection": 7.4,
      "confidence": 47.2,
      "ev": -12.4,
      "diff": -0.1,
      "market_odds": -117,
      "fair_odds": 112,
      "prob_edge": -6.7
    },
    {
      "player": "Amen Thompson",
      "team": "HOU",
      "prop": "AST",
      "direction": "OVER",
      "line": 5.5,
      "projection": 6.1,
      "confidence": 49.0,
      "ev": -5.2,
      "diff": 0.6,
      "market_odds": -107,
      "fair_odds": 104,
      "prob_edge": -2.7
    },
    {
      "player": "Amen Thompson",
      "team": "HOU",
      "prop": "PRA",
      "direction": "UNDER",
      "line": 30.5,
      "projection": 29.8,
      "confidence": 50.5,
      "ev": -3.6,
      "diff": -0.7,
      "market_odds": -110,
      "fair_odds": -102,
      "prob_edge": -1.9
    },
    {
      "player": "Kevin Durant",
      "team": "HOU",
      "prop": "PTS",
      "direction": "OVER",
      "line": 25.5,
      "projection": 27.8,
      "confidence": 50.5,
      "ev": -1.0,
      "diff": 2.3,
      "market_odds": -104,
      "fair_odds": -102,
      "prob_edge": -0.5
    },
    {
      "player": "Kevin Durant",
      "team": "HOU",
      "prop": "REB",
      "direction": "UNDER",
      "line": 5.5,
      "projection": 5.2,
      "confidence": 49.5,
      "ev": -15.4,
      "diff": -0.3,
      "market_odds": -141,
      "fair_odds": 102,
      "prob_edge": -9.0
    },
    {
      "player": "Kevin Durant",
      "team": "HOU",
      "prop": "AST",
      "direction": "OVER",
      "line": 4.5,
      "projection": 4.7,
      "confidence": 49.5,
      "ev": -10.3,
      "diff": 0.2,
      "market_odds": -123,
      "fair_odds": 102,
      "prob_edge": -5.7
    },
    {
      "player": "Kevin Durant",
      "team": "HOU",
      "prop": "PRA",
      "direction": "OVER",
      "line": 35.5,
      "projection": 38.0,
      "confidence": 51.4,
      "ev": -2.8,
      "diff": 2.5,
      "market_odds": -112,
      "fair_odds": -106,
      "prob_edge": -1.4
    },
    {
      "player": "Alperen Sengun",
      "team": "HOU",
      "prop": "PTS",
      "direction": "UNDER",
      "line": 20.5,
      "projection": 18.9,
      "confidence": 51.9,
      "ev": 2.2,
      "diff": -1.6,
      "market_odds": -103,
      "fair_odds": -108,
      "prob_edge": 1.2,
      "edge": "GOOD"
    },
    {
      "player": "Alperen Sengun",
      "team": "HOU",
      "prop": "REB",
      "direction": "OVER",
      "line": 8.5,
      "projection": 8.7,
      "confidence": 53.5,
      "ev": -6.8,
      "diff": 0.2,
      "market_odds": -135,
      "fair_odds": -115,
      "prob_edge": -3.9
    },
    {
      "player": "Alperen Sengun",
      "team": "HOU",
      "prop": "AST",
      "direction": "OVER",
      "line": 5.5,
      "projection": 6.0,
      "confidence": 52.6,
      "ev": -9.5,
      "diff": 0.5,
      "market_odds": -139,
      "fair_odds": -111,
      "prob_edge": -5.6
    },
    {
      "player": "Alperen Sengun",
      "team": "HOU",
      "prop": "PRA",
      "direction": "UNDER",
      "line": 36.5,
      "projection": 34.5,
      "confidence": 51.1,
      "ev": -6.4,
      "diff": -2.0,
      "market_odds": -120,
      "fair_odds": -104,
      "prob_edge": -3.4
    },
    {
      "player": "Naji Marshall",
      "team": "DAL",
      "prop": "PTS",
      "direction": "OVER",
      "line": 16.5,
      "projection": 19.0,
      "confidence": 52.0,
      "ev": 4.1,
      "diff": 2.5,
      "market_odds": -100,
      "fair_odds": -108,
      "prob_edge": 2.0,
      "edge": "GOOD"
    },
    {
      "player": "Naji Marshall",
      "team": "DAL",
      "prop": "REB",
      "direction": "OVER",
      "line": 4.5,
      "projection": 5.5,
      "confidence": 52.5,
      "ev": -9.1,
      "diff": 1.0,
      "market_odds": -137,
      "fair_odds": -111,
      "prob_edge": -5.3
    },
    {
      "player": "Naji Marshall",
      "team": "DAL",
      "prop": "AST",
      "direction": "OVER",
      "line": 3.5,
      "projection": 3.6,
      "confidence": 46.6,
      "ev": -12.1,
      "diff": 0.1,
      "market_odds": -113,
      "fair_odds": 115,
      "prob_edge": -6.5
    },
    {
      "player": "Naji Marshall",
      "team": "DAL",
      "prop": "PRA",
      "direction": "OVER",
      "line": 24.5,
      "projection": 28.2,
      "confidence": 50.6,
      "ev": -6.2,
      "diff": 3.7,
      "market_odds": -117,
      "fair_odds": -102,
      "prob_edge": -3.3
    },
    {
      "player": "P.J. Washington",
      "team": "DAL",
      "prop": "REB",
      "direction": "UNDER",
      "line": 6.0,
      "projection": 6.0,
      "confidence": 47.7,
      "ev": -11.2,
      "diff": -0.0,
      "market_odds": -116,
      "fair_odds": 110,
      "prob_edge": -6.0
    },
    {
      "player": "Cooper Flagg",
      "team": "DAL",
      "prop": "PTS",
      "direction": "OVER",
      "line": 19.5,
      "projection": 21.9,
      "confidence": 53.0,
      "ev": -2.0,
      "diff": 2.4,
      "market_odds": -118,
      "fair_odds": -113,
      "prob_edge": -1.1
    },
    {
      "player": "Cooper Flagg",
      "team": "DAL",
      "prop": "REB",
      "direction": "OVER",
      "line": 5.5,
      "projection": 6.1,
      "confidence": 51.6,
      "ev": -6.4,
      "diff": 0.6,
      "market_odds": -123,
      "fair_odds": -107,
      "prob_edge": -3.6
    },
    {
      "player": "Cooper Flagg",
      "team": "DAL",
      "prop": "AST",
      "direction": "UNDER",
      "line": 4.5,
      "projection": 4.3,
      "confidence": 51.3,
      "ev": -10.7,
      "diff": -0.2,
      "market_odds": -135,
      "fair_odds": -105,
      "prob_edge": -6.1
    },
    {
      "player": "Cooper Flagg",
      "team": "DAL",
      "prop": "PRA",
      "direction": "OVER",
      "line": 30.0,
      "projection": 31.5,
      "confidence": 50.5,
      "ev": -6.0,
      "diff": 1.5,
      "market_odds": -116,
      "fair_odds": -102,
      "prob_edge": -3.2
    }
  ]
}