{
  "date": "2026-02-24",
  "generated_at": "2026-02-24T12:28:32",
  "picks": [
    {
      "type": "prop",
      "player": "Evan Mobley",
      "team": "CLE",
      "prop": "REB",
      "direction": "OVER",
      "line": 6.5,
      "projection": 8.2,
      "diff": 1.7,
      "ev": 3.5,
      "confidence": 57.7,
      "pick_score": 55.1,
      "score_factors": [
        "+3.5% EV",
        "70% L10 hit rate",
        "5-game streak"
      ],
      "book_odds": {
        "fanduel": {
          "over": {
            "line": 6.5,
            "odds": -146
          },
          "under": {
            "line": 6.5,
            "odds": 110
          }
        },
        "draftkings": {
          "over": {
            "line": 6.5,
            "odds": -144
          },
          "under": {
            "line": 6.5,
            "odds": 109
          }
        },
        "betmgm": {
          "over": {
            "line": 7.5,
            "odds": 105
          },
          "under": {
            "line": 7.5,
            "odds": -140
          }
        }
      },
      "best_book": "betmgm",
      "insight": "Has gone OVER 6.5 rebounds in 7 of last 10 games (8.5 avg).",
      "top_pick_rank": 1,
      "result": "LOSS",
      "actual": 2
    },
    {
      "type": "total",
      "game": "UTA @ HOU",
      "away_team": "UTA",
      "home_team": "HOU",
      "pick": "OVER 226.5",
      "confidence": 79.3,
      "pick_score": 55.0,
      "score_factors": [
        "79.3% total conf",
        "Very high confidence"
      ],
      "commence_time": "2026-02-24T02:40:00Z",
      "top_pick_rank": 2
    },
    {
      "type": "prop",
      "player": "Nickeil Alexander-Walker",
      "team": "ATL",
      "prop": "AST",
      "direction": "OVER",
      "line": 3.5,
      "projection": 4.2,
      "diff": 0.7,
      "ev": 2.6,
      "confidence": 59.7,
      "pick_score": 54.6,
      "score_factors": [
        "+2.6% EV",
        "60% L10 hit rate",
        "Favorable matchup (#26 DEF)"
      ],
      "book_odds": {
        "fanduel": {
          "over": {
            "line": 3.5,
            "odds": -132
          },
          "under": {
            "line": 3.5,
            "odds": -100
          }
        },
        "draftkings": {
          "over": {
            "line": 3.5,
            "odds": -137
          },
          "under": {
            "line": 3.5,
            "odds": 104
          }
        },
        "betmgm": {
          "over": {
            "line": 3.5,
            "odds": -150
          },
          "under": {
            "line": 3.5,
            "odds": 110
          }
        }
      },
      "best_book": "fanduel",
      "insight": "On a 6-game OVER streak for assists.",
      "top_pick_rank": 3,
      "result": "WIN",
      "actual": 6
    },
    {
      "type": "spread",
      "game": "CLE @ CHA",
      "away_team": "CLE",
      "home_team": "CHA",
      "pick": "CHA +6.0",
      "confidence": 77.0,
      "pick_score": 50.0,
      "score_factors": [
        "77.0% spread conf",
        "High confidence"
      ],
      "commence_time": "2026-02-21T00:10:00Z",
      "top_pick_rank": 4
    },
    {
      "type": "ml",
      "game": "UTA @ MEM",
      "away_team": "UTA",
      "home_team": "MEM",
      "pick": "MEM",
      "confidence": 68.9,
      "pick_score": 50.0,
      "score_factors": [
        "68.9% ML conf"
      ],
      "commence_time": "2026-02-21T00:10:00Z",
      "top_pick_rank": 5
    }
  ]
}